brposNLTK/__init__.py
brposNLTK/pos_tagger.py
brposnltk-1.1.0.dist-info/METADATA
brposnltk-1.1.0.dist-info/WHEEL
brposnltk-1.1.0.dist-info/top_level.txt
brposnltk-1.1.0.dist-info/RECORD
